mbtiles_s3_server/__init__.py
mbtiles_s3_server/__main__.py
mbtiles_s3_server/glyphs.proto
mbtiles_s3_server/glyphs_pb2.py
mbtiles_s3_server/__pycache__/__init__.cpython-38.pyc
mbtiles_s3_server/__pycache__/__init__.cpython-39.pyc
mbtiles_s3_server/__pycache__/__main__.cpython-38.pyc
mbtiles_s3_server/__pycache__/__main__.cpython-39.pyc
mbtiles_s3_server/__pycache__/glyphs_pb2.cpython-38.pyc
mbtiles_s3_server/__pycache__/glyphs_pb2.cpython-39.pyc
mbtiles_s3_server/__pycache__/sqlite_s3_query.cpython-39.pyc
mbtiles_s3_server/vendor/dark-matter-gl-style@1.0.0/LICENSE.md
mbtiles_s3_server/vendor/dark-matter-gl-style@1.0.0/sprite.json
mbtiles_s3_server/vendor/dark-matter-gl-style@1.0.0/sprite.png
mbtiles_s3_server/vendor/dark-matter-gl-style@1.0.0/sprite@2x.json
mbtiles_s3_server/vendor/dark-matter-gl-style@1.0.0/sprite@2x.png
mbtiles_s3_server/vendor/dark-matter-gl-style@1.0.0/style.json
mbtiles_s3_server/vendor/fiord-color-gl-style@1.0.0/sprite.json
mbtiles_s3_server/vendor/fiord-color-gl-style@1.0.0/sprite.png
mbtiles_s3_server/vendor/fiord-color-gl-style@1.0.0/sprite@2x.json
mbtiles_s3_server/vendor/fiord-color-gl-style@1.0.0/sprite@2x.png
mbtiles_s3_server/vendor/fiord-color-gl-style@1.0.0/style.json
mbtiles_s3_server/vendor/fonts-gl@1.0.0/KlokanTech Noto Sans - LICENSE.txt
mbtiles_s3_server/vendor/fonts-gl@1.0.0/Metropolis - LICENSE.txt
mbtiles_s3_server/vendor/fonts-gl@1.0.0/Noto Sans - LICENSE.txt
mbtiles_s3_server/vendor/fonts-gl@1.0.0/Nunito - LICENSE.txt
mbtiles_s3_server/vendor/fonts-gl@1.0.0/Roboto - LICENSE.txt
mbtiles_s3_server/vendor/fonts-gl@1.0.0/fonts.tar.gz
mbtiles_s3_server/vendor/maplibre-gl@2.1.9/LICENSE.md
mbtiles_s3_server/vendor/maplibre-gl@2.1.9/maplibre-gl.css
mbtiles_s3_server/vendor/maplibre-gl@2.1.9/maplibre-gl.js
mbtiles_s3_server/vendor/maptiler-3d-gl-style@1.0.0/LICENSE.md
mbtiles_s3_server/vendor/maptiler-3d-gl-style@1.0.0/style.json
mbtiles_s3_server/vendor/maptiler-basic-gl-style@1.0.0/LICENSE.md
mbtiles_s3_server-0.0.20.dist-info/LICENSE
mbtiles_s3_server-0.0.20.dist-info/METADATA
mbtiles_s3_server-0.0.20.dist-info/WHEEL
mbtiles_s3_server-0.0.20.dist-info/top_level.txt
mbtiles_s3_server-0.0.20.dist-info/RECORD
