Metadata-Version: 2.1
Name: mbtiles-s3-server
Version: 0.0.20
Summary: Server to on-the-fly extract and serve vector tiles from an mbtiles file on S3
Home-page: https://github.com/uktrade/mbtiles-s3-server
Author: Department for International Trade
Author-email: sre@digital.trade.gov.uk
Classifier: Programming Language :: Python :: 3
Classifier: License :: OSI Approved :: MIT License
Classifier: License :: OSI Approved :: BSD License
Requires-Python: >=3.7.4
License-File: LICENSE
Requires-Dist: flask (>=2.0.0)
Requires-Dist: gevent (>=21.8.0)
Requires-Dist: protobuf (>=4.21.1)
Requires-Dist: sqlite-s3-query (>=0.0.68)
